[
  {
    "id": 1,
    "name": "Monkey 1",
    "autor": "Bored Ape Yacht Club",
    "photo": "public/api/images/monkey1.jpg",
    "price": 100,
    "year" : 2023
  },
  {
    "id": 2,
    "name": "Monkey 2",
    "autor": "Bored Ape Yacht Club",
    "photo": "public/api/images/monkey2.jpg",
    "year" : 2022,
    "price": 150
  },
  {
    "id": 3,
    "name": "Monkey 3",
    "autor": "Bored Ape Yacht Club",
    "photo": "images/monkey3.jpg",
    "year" : 2022,
    "price": 150
  },
  {
    "id": 4,
    "name": "Monkey 4",
    "autor": "Bored Ape Yacht Club",
    "photo": "images/monkey4.jpg",
    "year" : 2023,
    "price": 150
  },
  {
    "id": 5,
    "name": "Monkey 5",
    "autor": "Bored Ape Yacht Club",
    "photo": "images/monkey5.jpg",
    "year" : 2021,
    "price": 150
  },
  {
    "id": 6,
    "name": "Monkey 6",
    "autor": "Bored Ape Yacht Club",
    "photo": "images/monkey6.jpg",
    "year" : 2020,
    "price": 150
  },
  {
    "id": 7,
    "name": "Monkey 7",
    "autor": "Bored Ape Yacht Club",
    "photo": "images/monkey7.jpg",
    "year" : 2019,
    "price": 150
  },
  {
    "id": 2,
    "name": "Monkey 2",
    "autor": "Bored Ape Yacht Club",
    "photo": "images/monkey2.jpg",
    "year" : 2020,
    "price": 150
  },
  {
    "id": 8,
    "name": "Monkey 8",
    "autor": "Bored Ape Yacht Club",
    "photo": "images/monkey8.jpg",
    "year" : 2021,
    "price": 150
  },
  {
    "id": 9,
    "name": "Monkey 9",
    "autor": "Bored Ape Yacht Club",
    "photo": "images/monkey9.jpg",
    "year" : 2022,
    "price": 150
  }
]
